gha_runner/__init__.py
gha_runner/clouddeployment.py
gha_runner/gh.py
gha_runner/helper/__init__.py
gha_runner/helper/input.py
gha_runner/helper/workflow_cmds.py
gha_runner/templates/user-script.sh.templ
gha_runner-0.6.2.dist-info/licenses/LICENSE
gha_runner-0.6.2.dist-info/METADATA
gha_runner-0.6.2.dist-info/WHEEL
gha_runner-0.6.2.dist-info/top_level.txt
gha_runner-0.6.2.dist-info/RECORD
