Metadata-Version: 2.4
Name: gha_runner
Version: 0.6.2
Summary: A GitHub Runner for deploying on cloud backends
Author-email: Ethan Holz <ethan.holz@omsf.io>, "David W.H. Swenson" <david.swenson@omsf.io>
License: MIT License
Requires-Python: >=3.11
License-File: LICENSE
Requires-Dist: requests
Provides-Extra: test
Requires-Dist: pytest; extra == "test"
Requires-Dist: pytest-cov; extra == "test"
Requires-Dist: responses; extra == "test"
Provides-Extra: docs
Requires-Dist: mkdocs; extra == "docs"
Requires-Dist: mkdocstrings[python]; extra == "docs"
Requires-Dist: mkdocs-llmstxt; extra == "docs"
Dynamic: license-file
